log10/__init__.py
log10/completions.py
log10/feedback.py
log10/feedbacktasks.py
log10/sdk.py
log10/sdkconfiguration.py
log10/sessions.py
log10/_hooks/__init__.py
log10/_hooks/sdkhooks.py
log10/_hooks/types.py
log10/models/__init__.py
log10/models/components/__init__.py
log10/models/components/chatcompletionfunctioncalloption.py
log10/models/components/chatcompletionfunctions.py
log10/models/components/chatcompletionmessagetoolcall.py
log10/models/components/chatcompletionnamedtoolchoice.py
log10/models/components/chatcompletionrequestassistantmessage.py
log10/models/components/chatcompletionrequestfunctionmessage.py
log10/models/components/chatcompletionrequestmessage.py
log10/models/components/chatcompletionrequestmessagecontentpart.py
log10/models/components/chatcompletionrequestmessagecontentpartimage.py
log10/models/components/chatcompletionrequestmessagecontentparttext.py
log10/models/components/chatcompletionrequestsystemmessage.py
log10/models/components/chatcompletionrequesttoolmessage.py
log10/models/components/chatcompletionrequestusermessage.py
log10/models/components/chatcompletionresponsemessage.py
log10/models/components/chatcompletionrole.py
log10/models/components/chatcompletionstreamoptions.py
log10/models/components/chatcompletiontokenlogprob.py
log10/models/components/chatcompletiontool.py
log10/models/components/chatcompletiontoolchoiceoption.py
log10/models/components/completion.py
log10/models/components/completionusage.py
log10/models/components/createchatcompletionrequest.py
log10/models/components/createchatcompletionresponse.py
log10/models/components/feedback.py
log10/models/components/functionobject.py
log10/models/components/httpmetadata.py
log10/models/components/security.py
log10/models/components/session.py
log10/models/components/task.py
log10/models/errors/__init__.py
log10/models/errors/sdkerror.py
log10/models/internal/__init__.py
log10/models/internal/globals.py
log10/models/operations/__init__.py
log10py-0.1.0.dist-info/METADATA
log10py-0.1.0.dist-info/WHEEL
log10py-0.1.0.dist-info/top_level.txt
log10py-0.1.0.dist-info/RECORD
